calc/__init__.py
calc/calc.py
kcalculator-0.0.7.dist-info/LICENCE.txt
kcalculator-0.0.7.dist-info/METADATA
kcalculator-0.0.7.dist-info/WHEEL
kcalculator-0.0.7.dist-info/top_level.txt
kcalculator-0.0.7.dist-info/RECORD
